<?xml version="1.0" encoding="UTF-8"?>
<objects serializationModel="Studio.02.01.00">
	<object class="AudioFile" id="{a2fcafb2-568f-440a-9646-a77ef2b7a707}">
		<property name="assetPath">
			<value>walking_footsteps/footsteps_dirt_4.ogg</value>
		</property>
		<property name="frequencyInKHz">
			<value>48</value>
		</property>
		<property name="channelCount">
			<value>2</value>
		</property>
		<property name="length">
			<value>1.7</value>
		</property>
		<relationship name="masterAssetFolder">
			<destination>{2e228570-4344-4f51-8c4f-9209117258bb}</destination>
		</relationship>
	</object>
</objects>
